simpleregex/__init__.py
simpleregex/consts.py
simpleregex/func.py
simpleregex/models.py
simpleregex/tests/__init__.py
simpleregex/tests/test_any_of_characters.py
simpleregex/tests/test_email.py
simpleregex/tests/test_group.py
simpleregex/tests/test_look_ahead.py
simpleregex/tests/test_look_behind.py
simpleregex/tests/test_models.py
simpleregex/tests/test_negate.py
simpleregex/tests/test_none_or_many.py
simpleregex/tests/test_none_or_one.py
simpleregex/tests/test_one_or_more.py
simpleregex/tests/test_regex_or.py
simpleregex/tests/test_regex_range.py
simpleregex/tests/test_repeat.py
simpleregex/tests/test_times.py
simpleregex-0.1.10.dist-info/LICENSE
simpleregex-0.1.10.dist-info/METADATA
simpleregex-0.1.10.dist-info/WHEEL
simpleregex-0.1.10.dist-info/top_level.txt
simpleregex-0.1.10.dist-info/RECORD
