Metadata-Version: 2.1
Name: simpleregex
Version: 0.1.10
Summary: Wrapper for RegEx, made so the RegEx code will be understandable
Home-page: https://github.com/netguru/SimpleRegEx
Download-URL: https://pypi.org/project/simpleregex/
Author: Netguru
Author-email: hello@netguru.com
License: BSD-3-Clause
Project-URL: Documentation, https://github.com/netguru/SimpleRegEx/blob/main/docs/index.md
Project-URL: Source, https://github.com/netguru/SimpleRegEx
Project-URL: Tracker, https://github.com/netguru/SimpleRegEx/issues
Classifier: Environment :: MacOS X
Classifier: Environment :: Win32 (MS Windows)
Classifier: Environment :: X11 Applications
Classifier: Intended Audience :: Developers
Classifier: Operating System :: MacOS :: MacOS X
Classifier: Operating System :: Microsoft :: Windows
Classifier: Operating System :: POSIX :: Linux
Classifier: Programming Language :: Python :: 3.8
Classifier: Programming Language :: Python :: 3.9
Classifier: Programming Language :: Python :: 3.10
Classifier: Programming Language :: Python :: 3.11
Classifier: Topic :: Software Development :: Libraries :: Python Modules
License-File: LICENSE
